qinfpy/__init__.py
qinfpy/basic/__init__.py
qinfpy/basic/doLinCombMd.py
qinfpy/basic/dualMatMd.py
qinfpy/basic/getLogMd.py
qinfpy/basic/hermBasisMd.py
qinfpy/basic/isPSDMd.py
qinfpy/basic/isRightDimMd.py
qinfpy/basic/tenProdMd.py
qinfpy/basic/tenProdSelfMd.py
qinfpy/basic/zerOutMd.py
qinfpy/basic/zerOutNumMd.py
qinfpy/basic/pureState/__init__.py
qinfpy/basic/pureState/indexToKetMd.py
qinfpy/basic/pureState/ketTenQubitMd.py
qinfpy/basic/pureState/ketTenQubitTwoMd.py
qinfpy/basic/pureState/schmidtDecompMd.py
qinfpy/basic/pureState/stanBraMd.py
qinfpy/basic/pureState/stanKetMd.py
qinfpy-0.0.1.dist-info/LICENSE
qinfpy-0.0.1.dist-info/METADATA
qinfpy-0.0.1.dist-info/WHEEL
qinfpy-0.0.1.dist-info/top_level.txt
qinfpy-0.0.1.dist-info/RECORD
