Metadata-Version: 2.1
Name: qinfpy
Version: 0.0.1
Summary: A Python package for Quantum Information
Home-page: https://github.com/qinfpy
Author: Vikesh Siddhu
Author-email: vsiddhu@protonmail.com
License: BSD 3-Clause License
Platform: UNKNOWN
Classifier: Development Status :: 1 - Planning
Classifier: Programming Language :: Python :: 3
Classifier: License :: OSI Approved :: BSD License
Classifier: Operating System :: OS Independent
Classifier: Topic :: Scientific/Engineering :: Physics
Classifier: Topic :: Scientific/Engineering :: Mathematics
Requires-Python: >=3.6
